ultratechai_agent/__init__.py
ultratechai_agent/agent_router.py
ultratechai_agent/config_loader.py
ultratechai_agent/conflict_resolver.py
ultratechai_agent/feedback_engine.py
ultratechai_agent/memory_engine.py
ultratechai_agent/model_router.py
ultratechai_agent/self_healing_agent.py
ultratechai_agent-0.1.dist-info/METADATA
ultratechai_agent-0.1.dist-info/WHEEL
ultratechai_agent-0.1.dist-info/top_level.txt
ultratechai_agent-0.1.dist-info/RECORD
