Metadata-Version: 2.4
Name: ultratechai_agent
Version: 0.1
Summary: UltraTechAI Multi-Agent MAX Mode SDK
Home-page: https://ultratechai.store
Author: Elçin
Author-email: info@ultratechai.store
Dynamic: author
Dynamic: author-email
Dynamic: home-page
Dynamic: summary
